rusgram/__init__.py
rusgram-0.1.0.dist-info/licenses/LICENSE
rusgram-0.1.0.dist-info/METADATA
rusgram-0.1.0.dist-info/WHEEL
rusgram-0.1.0.dist-info/top_level.txt
rusgram-0.1.0.dist-info/RECORD
